{
  "positions": {
    "127.0.0.1:19132|Arthenyxx": {
      "x": 82.988625,
      "y": 78,
      "z": -170.48224,
      "saved_at": "2026-05-27T11:58:16.6331037+07:00"
    },
    "127.0.0.1:19132|Luna": {
      "x": 70.478035,
      "y": 72,
      "z": -173.08296,
      "saved_at": "2026-06-15T23:34:00.9350231+07:00"
    },
    "185.207.166.188:19132|.Arthenyxx": {
      "x": 133.47409,
      "y": 29,
      "z": -431.5342,
      "saved_at": "2026-06-03T18:33:45.9061655+07:00"
    },
    "185.207.166.188:19132|Luna": {
      "x": 0,
      "y": 67.38,
      "z": 0,
      "saved_at": "2026-06-03T18:32:28.0118436+07:00"
    },
    "185.207.166.219:19132|.Arthenyxx": {
      "x": 0.6218108,
      "y": 100,
      "z": 0.67726344,
      "saved_at": "2026-05-28T14:58:13.2515753+07:00"
    },
    "185.207.166.219:19132|Luna": {
      "x": 0,
      "y": 67.38,
      "z": 0,
      "saved_at": "2026-05-28T14:57:16.9407153+07:00"
    },
    "51.79.230.120:19132|Arthenyxx": {
      "x": -45.255863,
      "y": 116.001,
      "z": 744.78357,
      "saved_at": "2026-06-16T19:56:46.0609077+07:00"
    },
    "51.79.230.120:19132|Luna": {
      "x": -46.5,
      "y": 116.5,
      "z": 743.5,
      "saved_at": "2026-06-16T20:46:04.3271797+07:00"
    }
  }
}